Workbook

Sheet VA
A3: VARIANCE ANALYSIS | D3: FOR
A5: SL | B5: DESCRIPTION | C5: BUDGET | D5: ACTUAL | E5: VARIANCE
A39: NOTES :
A40: * | B40: Variance Analysis is prepared based on the 'Budget '.
A41: 1 | B41: Turnover & Profits
B42: Turnover is not reached budget still there is profit due to GD material and proc income
A43: 2 | B43: Cost of Sales (material)
B44: cost of Sales percentage is comparatively less due to GD material
A45: 3 | B45: Other Direct Cost
B46: Depreciation for machineries BD 26,015, Repairs to machineries BD 6,595
A47: 4 | B47: Direct Wages
B48: Direct wages is comparatively high due to new appointments
A49: 5 | B49: Other Income
B50: It includes Incineration income of BD 30,338
B51: Sale of fixed assets BD 1,570
A52: 7 | B52: General & Administration expenses
B53: It includes Depreciation for BD 1,600
B54: It includes Repairs and Maintenance to Vehicles for BD 3,828
A55: 10 | B55: Interest
B56: It includes interest on shareholders' loan BD 1,301
D58: - 1 -

Sheet BS&PL
A2: Balance Sheet as at
C4: Budget | D4: Actual
C5: BD. | D5: BD.
A56: Statement of Income and Profit & Loss A/c.
A57: For the period from
C59: Budget | D59: Actual
C60: BD. | D60: BD.
D83: - 2 -

Sheet PY
A2: =+'BS&PL'!A2 -> Balance Sheet as at
C4: As on | D4: As on
C5: BD. | D5: BD.
A55: Comparison -Statement of Income and Profit & Loss A/c.
A56: For the period from
C58: Year | D58: Year
C59: BD. | D59: BD.

Sheet CF
A2: Statement of Cash Flows for period from
D4: Cash flows
D6: (Bahraini Dinars)

Sheet EQT
A3: STATEMENT OF CHANGES IN EQUITY
A4: January 01 To July 31, 2019 | E4: (Bahraini Dinars)
B5: Share | C5: Capital | D5: Legal | E5: Retained | F5: Total
B6: Capital | C6: Reserve | D6: Reserve | E6: earnings
A9: Balance as on 31-12-2008 | B9: 600000 | C9: 0 | D9: 300000 | E9: 1232033.7 | F9: 2132033.7
A10: Interim Dividends paid- Year 2009 | E10: =-140000 -> -140000 | F10: =E10 -> -140000
A11: Profit from Jan to Dec 2009 | E11: 720351.96 | F11: =E11 -> 720351.96
A12: Balance as on 31-12-2009 | B12: =SUM(B9:B11) -> 600000 | C12: =SUM(C9:C11) -> 0 | D12: =SUM(D9:D11) -> 300000 | E12: =SUM(E9:E11) -> 1812385.7 | F12: =SUM(F9:F11) -> 2712385.7
A13: Final Dividends paid- Year 2009 | E13: =-310000 -> -310000 | F13: =E13 -> -310000
A14: Interim Dividends paid- Year 2010 | E14: =-200000 -> -200000 | F14: =E14 -> -200000
A15: Profit from Jan to Dec 2010 | E15: 1159461.1 | F15: =E15 -> 1159461.1
A16: Balance as on 31-12-2010 | B16: =SUM(B12:B15) -> 600000 | C16: =SUM(C12:C15) -> 0 | D16: =SUM(D12:D15) -> 300000 | E16: =SUM(E12:E15) -> 2461846.7 | F16: =SUM(F12:F15) -> 3361846.7
A17: Final Dividends paid- Year 2010 | E17: -360000 | F17: =E17 -> -360000
A18: Interim Dividends paid- Year 2011 | E18: -450000 | F18: =E18 -> -450000
A19: Profit from Jan to Dec 2011 | E19: 1138318 | F19: =E19 -> 1138318
A20: Balance as in 31-12-2011 | B20: =SUM(B16:B19) -> 600000 | C20: =SUM(C16:C19) -> 0 | D20: =SUM(D16:D19) -> 300000 | E20: =SUM(E16:E19) -> 2790164.7 | F20: =SUM(F16:F19) -> 3690164.7
A21: Final Dividends paid- Year 2011 | E21: =-110000 -> -110000 | F21: =E21 -> -110000
A22: Final Dividends paid- Year 2012 | E22: =-350000 -> -350000 | F22: =E22 -> -350000
A23: Profit from Jan to Dec 2012 | E23: 537387.38 | F23: =E23 -> 537387.38
A24: Balance as on 31-12-2012 | B24: =SUM(B20:B23) -> 600000 | C24: =SUM(C20:C23) -> 0 | D24: =SUM(D20:D23) -> 300000 | E24: =SUM(E20:E23) -> 2867552.1 | F24: =SUM(F20:F23) -> 3767552.1 | T24: not done
A25: Interim Dividends paid- Year 2013 | E25: 0 | F25: =E25 -> 0
A26: Final Dividends paid- Year 2013 | E26: 0 | F26: =E26 -> 0
A27: Profit from Jan to Dec 2013 | E27: 492395.07 | F27: 492395.07
A28: Balance as on 31-12-2013 | B28: =SUM(B24:B27) -> 600000 | C28: =SUM(C24:C27) -> 0 | D28: =SUM(D24:D27) -> 300000 | E28: =SUM(E24:E27) -> 3359947.2 | F28: =SUM(F24:F27) -> 4259947.2
A29: Interim Dividends paid- Year 2014 | E29: 0 | F29: 0
A30: Final Dividends paid- Year 2014
A31: Profit - Year to Date | E31: 142945.02 | F31: =E31 -> 142945.02
A32: Balance as on 31-12-2014 | B32: =SUM(B28:B31) -> 600000 | C32: =SUM(C28:C31) -> 0 | D32: =SUM(D28:D31) -> 300000 | E32: =SUM(E28:E31) -> 3502892.2 | F32: =SUM(F28:F31) -> 4402892.2 | G32: 7666 | H32: 4.3 m bd | I32: book value of equity | L32: for drms by essa najibi
A33: Interim Dividends paid- Year 2015 | E33: 0 | F33: 0 | I33: average turn over of last 3 years
A34: Final Dividends paid- Year 2015 | E34: 0 | F34: 0
A35: Profit - Year to Date | E35: =319117+7667 -> 326784 | F35: =E35 -> 326784
A36: Balance as on 31-12-2015 | B36: =SUM(B32:B35) -> 600000 | C36: =SUM(C32:C35) -> 0 | D36: =SUM(D32:D35) -> 300000 | E36: =SUM(E32:E35) -> 3829676.2 | F36: =SUM(F32:F35) -> 4729676.2
A37: Interim Dividends paid- Year 2016 | E37: 0 | F37: 0
A38: Final Dividends paid- Year 2016 | E38: 0 | F38: 0
A39: Profit - Year to Date | E39: 524074.48 | F39: =E39 -> 524074.48
A40: Balance as on 31-12-2016 | B40: =SUM(B36:B39) -> 600000 | C40: =SUM(C36:C39) -> 0 | D40: =SUM(D36:D39) -> 300000 | E40: =SUM(E36:E39) -> 4353750.7 | F40: =SUM(F36:F39) -> 5253750.7
A41: Interim Dividends paid- Year 2017
A42: Final Dividends paid- Year 2017
A43: Profit - Year to Date | E43: =604624-7.05 -> 604616.95 | F43: =+E43 -> 604616.95
A44: Balance as on 31-12-2017 | B44: =SUM(B40:B43) -> 600000 | C44: =SUM(C40:C43) -> 0 | D44: =SUM(D40:D43) -> 300000 | E44: =SUM(E40:E43) -> 4958367.6 | F44: =SUM(F40:F43) -> 5858367.6
A45: Interim Dividends paid- Year 2018
A46: Provision as per IFRS-9 (Accumulated loss -CSM Subsidiary) & other receivables. | E46: =-293595-109858 -> -403453 | F46: =E46 -> -403453
A47: Profit - Year to Date | E47: =647036.665-27281 -> 619755.67 | F47: =+E47 -> 619755.67
A48: Balance as on 31-12-2018 | B48: =SUM(B44:B47) -> 600000 | C48: =SUM(C44:C47) -> 0 | D48: =SUM(D44:D47) -> 300000 | E48: =SUM(E44:E47) -> 5174670.3 | F48: =SUM(F44:F47) -> 6074670.3
A50: Interim Dividends paid- Year 2019
A51: Final Dividends paid- Year 2019
A52: Profit - Year to Date | E52: ='BS&PL'!D74 -> 0 | F52: =E52 -> 0
B54: =SUM(B48:B53) -> 600000 | C54: =SUM(C48:C53) -> 0 | D54: =SUM(D48:D53) -> 300000 | E54: =SUM(E48:E53) -> 5174670.3 | F54: =SUM(F48:F53) -> 6074670.3 | G54: =SUM(G40:G53) -> 0 | H54: =SUM(H40:H53) -> 0 | I54: =SUM(I40:I53) -> 0 | J54: =SUM(J40:J53) -> 0 | K54: =SUM(K40:K53) -> 0 | L54: =SUM(L40:L53) -> 0 | M54: =SUM(M40:M53) -> 0 | N54: =SUM(N40:N53) -> 0 | ... P54: =SUM(P40:P53) -> 0
E56: - 6 -

Sheet BSSH
A1: SCHEDULE ANNEXED TO BALANCE SHEET AS AT
A3: Sl | B3: Description | C3: Remarks | D3: Amount

Sheet RECV
A2: RECEIVABLE FROM RELATED PARTIES | C2: AS ON
A3: SL | B3: NAME OF PARTY | C3: REMARKS | D3: AMOUNT (BD.)

Sheet EXP
A1: DIRECT EXPENSES | C1: FOR
A2: SL NO. | B2: DESCRIPTION | C2: AMOUNT (BD.)
A101: GENERAL & ADMINISTRATIVE EXPENSES (FIXED EXPENSES)
A102: SL NO. | B102: DESCRIPTION | C102: AMOUNT (BD.)

Sheet DRS
A2: TRADE DEBTORS AS ON
A3: EXPORT
A4: SL NO. | B4: CUSTOMERS NAME | C4: AMOUNT(BD.)

Sheet ADV
A2: ADVANCE TO SUPPLIERS | C2: AS ON 31 JULY 2019
A3: SL.NO. | B3: NAME OF SUPPLIERS | C3: AMOUNT
A4: 1 | B4: INCI PROJ ENGR | C4: 29.1
A5: 2 | B5: JSR INTERNATIONAL FZC | C5: =29.601+0.434 -> 30.035
A6: 3 | B6: PROFESSIONS AUTO REPAIRS | C6: 50
A7: 4 | B7: CAPITAL MUNICIPALITY | C7: 100
A8: 5 | B8: FAMCO(AL-FUTTAIM AUTO&MACH CO) | C8: 100.05
A9: 6 | B9: JF HILLEBRAND MIDDLE EAST LLC | C9: 207
A10: 7 | B10: JV INTERNATIONAL (RAJIV GUPTA) | C10: 217.092
A11: 8 | B11: B.R.C.WELDMESH(GULF)W.L.L | C11: 267.4 | Q11: not done
A12: 9 | B12: AL SAIE INFORMATION TECHNOLOGY | C12: 307.146
A13: 10 | B13: AMAN ALMADINA ADVERTISING CO | C13: 370
A14: 11 | B14: BUREAU VERITAS BAHRAIN | C14: 370
A15: 12 | B15: Alyusuf Aluminum W.L.L | C15: 378
A16: 13 | B16: MOHAMMAD BIN JASIM AL ZAYANI | C16: 401
A17: 14 | B17: SHIVA INTERNATIONAL- BAHL B L | C17: 404.555
A18: 15 | B18: AL JEBEL SCRAP | C18: 415.99
A19: 16 | B19: ARABIAN MARINAS CO | C19: 445.42
A20: 17 | B20: NASS CORPORATION | C20: 467.265
A21: 18 | B21: TOP5 FABRICATION WORKSHOP | C21: 495
A22: 19 | B22: AL SANGAL CONSTRUCTION EST | C22: 812
A23: 20 | B23: MUHD TALHA RIAZ(AYSHA SCRAP) | C23: 845.411
... A57: 54 | B57: YAQEEN ALUMINIUM | C57: 1362.5
C59: =SUM(C4:C58) -> 530862.14
B60: PROVISION MADE FOR DOUBTFUL DEBTS
A61: 1 | B61: AL MANAR ESTABLISHMENT
A62: 2 | B62: HABIB G H MEAR
A63: 3 | B63: MOHAMMED ASGHAR | O63: DIFF
A64: 4 | B64: P.S.ABRAHAM (MAGIC TRDG) | D64: 22737.05 | E64: 21222.14 | F64: =D64-E64 -> 1514.91 | G64: PS RECOVERY | O64: 12.92
A65: 5 | B65: MEER TRADING(NASER H MEER)
C66: =SUM(C61:C65) -> 0
B67: TOTAL | C67: =C66+C59 -> 530862.14
B68: LESS: PROVISION FOR DOUBTFUL DEBTS | C68: =-C66 -> 0
B69: GRAND TOTAL | C69: =SUM(C67:C68) -> 530862.14
C71: - 13 -
A76: CROWN INDUSTRIES W.L.L., BAHRAIN
A77: RECEIVABLE FROM RELATED PARTIES
A78: SL | B78: NAME OF PARTY | C78: AMOUNT (BD.)
A79: 1 | B79: =RECV!B4 -> 0 | C79: =RECV!D4 -> 0
A80: 2 | B80: =RECV!B5 -> 0 | C80: =RECV!D5 -> 0
A81: 3 | B81: =RECV!B6 -> 0 | C81: =RECV!D6 -> 0
A82: 4 | B82: =RECV!B7 -> 0 | C82: =RECV!D7 -> 0
A83: 5 | B83: =RECV!B8 -> 0 | C83: =RECV!D8 -> 0
A84: 6 | B84: =RECV!B9 -> 0 | C84: =RECV!D9 -> 0
A85: 7 | B85: =RECV!B10 -> 0 | C85: =RECV!D10 -> 0
A86: 8 | B86: =RECV!B11 -> 0 | C86: =RECV!D11 -> 0
A87: 9 | B87: =RECV!B12 -> 0 | C87: =RECV!D12 -> 0
A88: 10 | B88: =RECV!B13 -> 0 | C88: =RECV!D13 -> 0
A89: 11 | B89: =RECV!B14 -> 0 | C89: =RECV!D14 -> 0
A90: 12 | B90: =RECV!B15 -> 0 | C90: =RECV!D15 -> 0
A91: 13 | B91: =RECV!B16 -> 0 | C91: =RECV!D16 -> 0
B92: =RECV!#REF! -> #REF!
B93: =RECV!B17 -> 0 | C93: =SUM(C79:C92) -> 0
A96: PAYABLE TO RELATED PARTIES
A97: SL | B97: NAME OF PARTY | C97: AMOUNT (BD.)
A98: 1 | B98: =RECV!B22 -> 0 | C98: =RECV!D22 -> 0
A99: 2 | B99: =RECV!B23 -> 0 | C99: =RECV!D23 -> 0
A100: 3 | B100: =RECV!B24 -> 0 | C100: =RECV!D24 -> 0
A101: 4 | B101: =RECV!B25 -> 0 | C101: =RECV!D25 -> 0
A102: 5 | B102: =RECV!B26 -> 0 | C102: =RECV!D26 -> 0
A103: 6 | B103: =RECV!B27 -> 0 | C103: =RECV!D27 -> 0
A104: 7 | B104: =RECV!B28 -> 0 | C104: =RECV!D28 -> 0
C106: =SUM(C98:C104) -> 0

Sheet CRS
A2: LIST OF CREDITORS AS ON
A3: S NO. | B3: DESCRIPTION | D3: AMOUNT
B163: TOTAL | C163: =SUM(C4:C162) -> 0
C165: - 17 -

Sheet P&L
A3: PROFIT & LOSS ACCOUNT FROM JANUARY TO JULY 2019 (YTD)
A5: SL. | B5: DESCRIPTION | C5: JAN | D5: FEB | E5: MAR | F5: APR | G5: MAY | H5: JUN | I5: JUL | J5: AUG | K5: SEP | L5: OCT | M5: NOV | N5: DEC | O5: TOTAL
A6: 1 | B6: REVENUE | C6: 344423.45 | D6: 688646.57 | E6: 872097.42 | F6: 705935.92 | G6: 750392.8 | H6: 691891.42 | I6: =VA!D6 -> 0 | O6: =SUM(C6:N6) -> 4053387.6
A7: 2 | B7: COST OF SALES | C7: -239489.89 | D7: -535742.74 | E7: -632895.41 | F7: -474862.6 | G7: -487578.59 | H7: -411320.95 | I7: =VA!D7 -> 0 | O7: =SUM(C7:N7) -> -2781890.2
A8: 3 | B8: OTHER DIRECT COSTS | C8: -90645 | D8: -86939.954 | E8: -94346.844 | F8: -85683.155 | G8: -88777.067 | H8: -86707.391 | I8: =VA!D8 -> 0 | O8: =SUM(C8:N8) -> -533099.41 | R8: not done
A9: 4 | B9: DIRECT WAGES | C9: -37558.2 | D9: -50600.208 | E9: -41319.828 | F9: -41980.929 | G9: -42161.551 | H9: -44618.88 | I9: =VA!D9 -> 0 | O9: =SUM(C9:N9) -> -258239.6
B10: GROSS PROFIT | C10: -23269.638 | D10: 15363.664 | E10: 103535.34 | F10: 103409.24 | G10: 131875.59 | H10: 149244.21 | I10: =SUM(I6:I9) -> 0 | J10: =SUM(J6:J9) -> 0 | K10: =SUM(K6:K9) -> 0 | L10: =SUM(L6:L9) -> 0 | M10: =SUM(M6:M9) -> 0 | N10: =SUM(N6:N9) -> 0 | O10: =SUM(O6:O9) -> 480158.41
A11: 5 | B11: OTHER INCOME | C11: 24053.555 | D11: 63214.415 | E11: 109811.33 | F11: 27609.172 | G11: 14077.114 | H11: 64161.932 | I11: =VA!D11 -> 0 | O11: =SUM(C11:N11) -> 302927.52
A12: 6 | B12: SELLING EXPENSES | C12: -1228 | D12: -2870.442 | E12: -4102.769 | F12: -2837.575 | G12: -5872.115 | H12: -2782.272 | I12: =VA!D12 -> 0 | O12: =SUM(C12:N12) -> -19693.173
A13: 7 | B13: GENERAL & ADMINISTRATIVE | C13: -44236 | D13: -43544.723 | E13: -42345.759 | F13: -56883.113 | G13: -43648.84 | H13: -49908.973 | I13: =VA!D13 -> 0 | O13: =SUM(C13:N13) -> -280567.41
A14: 8 | B14: ADMINISTRATIVE SALARY | C14: -21955.9 | D14: -22288.1 | E14: -20537.916 | F14: -19685.9 | G14: -21818.459 | H14: -18841.675 | I14: =VA!D14 -> 0 | O14: =SUM(C14:N14) -> -125127.95
A15: 9 | B15: OTHER OP. EXPENSES | C15: 0 | D15: 0 | E15: 0 | F15: 0 | G15: 0 | H15: 0 | I15: =VA!D15 -> 0 | O15: =SUM(C15:N15) -> 0
B16: PROFIT FM OPERATIONS | C16: -66635.983 | D16: 9874.814 | E16: 146360.23 | F16: 51611.823 | G16: 74613.294 | H16: 141873.22 | I16: =SUM(I10:I15) -> 0 | J16: =SUM(J10:J15) -> 0 | K16: =SUM(K10:K15) -> 0 | L16: =SUM(L10:L15) -> 0 | M16: =SUM(M10:M15) -> 0 | N16: =SUM(N10:N15) -> 0 | O16: =SUM(O10:O15) -> 357697.4
A17: 10 | B17: BANK INTEREST | C17: -6820.302 | D17: -6125.368 | E17: -7749.65 | F17: -7836.489 | G17: -8138.128 | H17: -10906.151 | I17: =VA!D17 -> 0 | O17: =SUM(C17:N17) -> -47576.088
B19: NET PROFIT / LOSS | C19: =SUM(C16:C17) -> -73456.285 | D19: =SUM(D16:D17) -> 3749.446 | E19: =SUM(E16:E17) -> 138610.58 | F19: =SUM(F16:F17) -> 43775.334 | G19: =SUM(G16:G17) -> 66475.166 | H19: =SUM(H16:H17) -> 130967.07 | I19: =SUM(I16:I17) -> 0 | J19: =SUM(J16:J17) -> 0 | ... O19: =SUM(O16:O17) -> 310121.31
B20: ACCUMULATED YTD PROFIT/LOSS | C20: =C19 -> -73456.285 | D20: =C20+D19 -> -69706.839 | E20: =D20+E19 -> 68903.739 | F20: =E20+F19 -> 112679.07 | G20: =F20+G19 -> 179154.24 | H20: =G20+H19 -> 310121.31 | I20: =H20+I19 -> 310121.31 | N20: =N19 -> 0
B22: GROSS PROFIT RATIO | C22: =+C10/C6*100 -> -6.7561131 | D22: =+D10/D6*100 -> 2.230994 | E22: =+E10/E6*100 -> 11.871993 | F22: =+F10/F6*100 -> 14.648531 | G22: =+G10/G6*100 -> 17.574208 | H22: =+H10/H6*100 -> 21.570467 | I22: =+I10/I6*100 -> #DIV/0! | J22: =+J10/J6*100 -> #DIV/0! | ... O22: =+O10/O6*100 -> 11.845855
B24: NET PROFIT RATIO | C24: =+C19/C6*100 -> -21.327318 | D24: =+D19/D6*100 -> 0.54446594 | E24: =+E19/E6*100 -> 15.893933 | F24: =+F19/F6*100 -> 6.201035 | G24: =+G19/G6*100 -> 8.8587158 | H24: =+H19/H6*100 -> 18.928847 | I24: =+I19/I6*100 -> #DIV/0! | J24: =+J19/J6*100 -> #DIV/0! | ... O24: =+O19/O6*100 -> 7.6509167
B26: COST OF SALES % | C26: =100-C22 -> 106.75611 | D26: =100-D22 -> 97.769006 | E26: =100-E22 -> 88.128007 | F26: =100-F22 -> 85.351469 | G26: =100-G22 -> 82.425792 | H26: =100-H22 -> 78.429533 | I26: =100-I22 -> #DIV/0! | J26: =100-J22 -> #DIV/0! | ... O26: =100-O22 -> 88.154145
B28: MATERIAL COST | C28: =-C7/C6% -> 69.533561 | D28: =-D7/D6% -> 77.796473 | E28: =-E7/E6% -> 72.571641 | F28: =-F7/F6% -> 67.267097 | G28: =-G7/G6% -> 64.976448 | H28: =-H7/H6% -> 59.44877 | I28: =-I7/I6% -> #DIV/0! | J28: =-J7/J6% -> #DIV/0! | ... O28: =-O7/O6% -> 68.63124
B34: other exps-qatar tender | C34: =C8+C9+C12+C13+C14+C15+C17-C35 -> -202443.4 | O34: =O8+O9+O12+O13+O14+O15+O17-O35 -> -1264303.6
B35: other exps-qatar tender | C35: 0 | O35: =SUM(C35:C35) -> 0 | P35: 0
B36: cogs | C36: =C7 -> -239489.89 | O36: =O7 -> -2781890.2
B37: income | C37: =C6+C11 -> 368477.01 | O37: =O6+O11 -> 4356315.1
B39: np | C39: =SUM(C34:C38) -> -73456.285 | O39: =SUM(O34:O38) -> 310121.31 | P39: =SUM(P34:P38) -> 0

Sheet ASSET
A3: SL | B3: MONTH | C3: ADMIN | D3: DIRECT | E3: TOTAL
A4: 1 | B4: JAN | C4: 1600 | D4: =2149.875+889.659+15288.42+736.593+7604.427+285.915+908.228-1600 -> 26263.117 | E4: =SUM(C4:D4) -> 27863.117
A5: 2 | B5: FEB | C5: 1600 | D5: =1815.353+803.563+13902.586+665.549+6931.818+258.245+833.486-1600 -> 23610.6 | E5: =SUM(C5:D5) -> 25210.6
A6: 3 | B6: MAR | C6: 1600 | D6: =1814.453+889.659+15351.957+736.858+7710.738+285.915+928.472-1600 -> 26118.052 | E6: =SUM(C6:D6) -> 27718.052 | J6: not done
A7: 4 | B7: APR | C7: 1600 | D7: =1635.551+860.96+14054.655+713.088+7462.003+276.691+929.024-1600 -> 24331.972 | E7: =SUM(C7:D7) -> 25931.972
A8: 5 | B8: MAY | C8: 1600 | D8: =1682.174+889.659+14677.128+736.858+7709.733+285.915+990.093-1600 -> 25371.56 | E8: =SUM(C8:D8) -> 26971.56
A9: 6 | B9: JUN | C9: 1600 | D9: =1627.911+860.96+14419.362+713.088+7310.77+276.691+946.142-1600 -> 24554.924 | E9: =SUM(C9:D9) -> 26154.924
A10: 7 | B10: JUL | C10: 1600 | D10: =1682.174+889.659+15271.481+736.858+7918.858+285.915+829.825-1600 -> 26014.77 | E10: =SUM(C10:D10) -> 27614.77
A11: 8 | B11: AUG | E11: =SUM(C11:D11) -> 0
A12: 9 | B12: SEP | E12: =SUM(C12:D12) -> 0
A13: 10 | B13: OCT | E13: =SUM(C13:D13) -> 0
A14: 11 | B14: NOV | E14: =SUM(C14:D14) -> 0
A15: 12 | B15: DEC | E15: =SUM(C15:D15) -> 0
C16: =SUM(C4:C15) -> 11200 | D16: =SUM(D4:D15) -> 176264.99 | E16: =SUM(E4:E15) -> 187464.99

Sheet GRAPH
A1: GROSS
A2: SL | B2: MONTH | C2: 43466 | D2: 43497 | E2: 43525 | F2: 43556 | G2: 43586 | H2: 43617 | I2: 43647 | J2: 43678 | K2: 43709 | L2: 43739 | M2: 43770 | N2: 43800
A3: 1 | B3: SALES | C3: ='P&L'!C6 -> 344423.45 | D3: ='P&L'!D6 -> 688646.57 | E3: ='P&L'!E6 -> 872097.42 | F3: ='P&L'!F6 -> 705935.92 | G3: ='P&L'!G6 -> 750392.8 | H3: ='P&L'!H6 -> 691891.42 | I3: ='P&L'!I6 -> 0 | J3: ='P&L'!J6 -> 0 | ... N3: ='P&L'!N6 -> 0
A4: 2 | B4: GROSS PROFIT | C4: ='P&L'!C10 -> -23269.638 | D4: ='P&L'!D10 -> 15363.664 | E4: ='P&L'!E10 -> 103535.34 | F4: ='P&L'!F10 -> 103409.24 | G4: ='P&L'!G10 -> 131875.59 | H4: ='P&L'!H10 -> 149244.21 | I4: ='P&L'!I10 -> 0 | J4: ='P&L'!J10 -> 0 | ... N4: ='P&L'!N10 -> 0
A5: 3 | B5: NET PROFIT | C5: ='P&L'!C19 -> -73456.285 | D5: ='P&L'!D19 -> 3749.446 | E5: ='P&L'!E19 -> 138610.58 | F5: ='P&L'!F19 -> 43775.334 | G5: ='P&L'!G19 -> 66475.166 | H5: ='P&L'!H19 -> 130967.07 | I5: ='P&L'!I19 -> 0 | J5: ='P&L'!J19 -> 0 | ... N5: ='P&L'!N19 -> 0

Sheet tb
A1: level | B1: ctrldiv | C1: ctrlaccode | D1: division | E1: accode | F1: acname | G1: actype | H1: acbal
F2: New | H2: 0
A3: 02 | F3: FIXED ASSETS | H3: 0
B4: GA | C4: 1510 | D4: GA | E4: 1510 | F4: LAND AT RAS ZUWAYED | G4: ASSET | H4: 124800
B5: GA | C5: 1511 | D5: GA | E5: 1511 | F5: BUILDINGS | G5: ASSET | H5: 69928.954
B6: GA | C6: 1521 | D6: GA | E6: 1521 | F6: PLANT & MACHINERY | G6: ASSET | H6: 1446048.6
B7: GA | C7: 1531 | D7: GA | E7: 1531 | F7: VEHICLES | G7: ASSET | H7: 598362.77
B8: GA | C8: 1541 | D8: GA | E8: 1541 | F8: FURNITURE & FIXTURES | G8: ASSET | H8: 55608.965
B9: CA | C9: 1551 | D9: CA | E9: 1551 | F9: CAPITAL WORK IN PROGRESS | G9: ASSET | H9: 1772189.5
B10: GA | C10: 1551 | D10: GA | E10: 1551 | F10: COMPUTER AND OFFICE EQUIPMENT | G10: ASSET | H10: 8775.148 | M10: not done
A11: 02 | F11: CURRENT ASSETS | H11: 0
A12: 03 | F12: INVENTORIES | H12: 0
B13: CA | C13: 1401 | D13: CA | E13: 1401 | F13: INVENTORY - BALANCE | G13: ASSET | H13: 1175103.5
B14: CA | C14: 1405 | D14: CA | E14: 1405 | F14: INVENTORY - SOLD | G14: ASSET | H14: -13130249
B15: CA | C15: 1410 | D15: CA | E15: 1410 | F15: INVENTORY - PURCHASE | G15: ASSET | H15: 13105114 | I15: =SUM(H13:H15) -> 1149968.2 | J15: 1149601 | K15: =J15-I15 -> -367.21 | L15: diff
A16: 03 | F16: MISCELLANEOUS ASSETS | H16: 0
B17: GA | C17: 1301 | D17: GA | E17: 1301 | F17: TRIVIAL ASSETS | G17: ASSET | H17: 2
B18: GA | C18: 1311 | D18: GA | E18: 1311 | F18: EQUIPMENTS & TOOLS IN USE | G18: ASSET | H18: 3009.032
B19: GA | C19: 1321 | D19: GA | E19: 1321 | F19: CONSUMABLE STORES | G19: ASSET | H19: 35238.911
B20: GA | C20: 1352 | D20: GA | E20: 1352 | F20: VAT INPUT | G20: ASSET | H20: 76774.612
A21: 03 | F21: INVESTMENTS | H21: 0
B22: GA | C22: 1391 | D22: GA | E22: 1391 | F22: LONA REAL ESTATE B.S.C(c) | G22: ASSET | H22: 350000
B23: GA | C23: 1392 | D23: GA | E23: 1392 | F23: LIGHT IND.LAND-A/C200016-CMH | G23: ASSET | H23: 188352.5
B24: GA | C24: 1393 | D24: GA | E24: 1393 | F24: SARAAT TOWER W.L.L | G24: ASSET | H24: 325260
B25: GA | C25: 1394 | D25: GA | E25: 1394 | F25: CROWN STEELMOULD-CSM | G25: ASSET | H25: 1035500
B26: GA | C26: 1395 | D26: GA | E26: 1395 | F26: SHK YARD- JENAN | G26: ASSET | H26: 230000
A27: 03 | F27: ACCOUNTS RECEIVABLE | H27: 0
B28: IA | C28: 1211 | D28: IA | E28: 1211 | F28: TRADE DEBTORS A/C | G28: ASSET | H28: 765507.69
B29: GA | C29: 1225 | D29: GA | E29: 1225 | F29: UNEXPIRED EXPS-VEH INSURANCE | G29: ASSET | H29: 12778.2
B30: GA | C30: 1226 | D30: GA | E30: 1226 | F30: PRE-PAID EXPENSES | G30: ASSET | H30: 29049.281
B31: GA | C31: 1228 | D31: GA | E31: 1228 | F31: UNEXPIRED EXPENSES - GEN | G31: ASSET | H31: 4280
B32: CA | C32: 1231 | D32: CA | E32: 1231 | F32: SALARY ADVANCE/LOAN | G32: ASSET | H32: 550
B33: CA | C33: 1232 | D33: CA | E33: 1232 | F33: SALARY ADVANCE/LOAN | G33: ASSET | H33: 250
B34: CA | C34: 1233 | D34: CA | E34: 1233 | F34: SALARY ADVANCE/LOAN | G34: ASSET | H34: 536.118
B35: CA | C35: 1234 | D35: CA | E35: 1234 | F35: SALARY ADVANCE/LOAN | G35: ASSET | H35: 3018.685
B36: CA | C36: 1235 | D36: CA | E36: 1235 | F36: SALARY ADVANCE/LOAN | G36: ASSET | H36: 3473.696
B37: CA | C37: 1236 | D37: CA | E37: 1236 | F37: SALARY ADVANCE/LOAN | G37: ASSET | H37: 530
B38: CA | C38: 1238 | D38: CA | E38: 1238 | F38: SALARY ADVANCE/LOAN | G38: ASSET | H38: 711.248
B39: CA | C39: 1240 | D39: CA | E39: 1240 | F39: SALARY ADVANCE/LOAN | G39: ASSET | H39: 735
... B64: CA | C64: 1275 | D64: CA | E64: 1275 | F64: SUSPENSE A/C- KSA NF JV PROJ | G64: ASSET | H64: 35406.756
A65: 03 | F65: CASH & BANK BALANCES | H65: 0
B66: GA | C66: 1101 | D66: GA | E66: 1101 | F66: PETTY CASH IMPREST A/C | G66: ASSET | H66: -1994.335
B67: GA | C67: 1111 | D67: GA | E67: 1111 | F67: CASH FOR PURCHASE | G67: ASSET | H67: 33046.401
B68: GA | C68: 1121 | D68: GA | E68: 1121 | F68: AHLI UNITED BANK-USD | G68: ASSET | H68: 25184.711
B69: GA | C69: 1122 | D69: GA | E69: 1122 | F69: AHLI UNITED BANK-BHD | G69: ASSET | H69: -124864.75
B70: GA | C70: 1124 | D70: GA | E70: 1124 | F70: STANDARD CHARTERED BANK-USD | G70: ASSET | H70: 2.138
B71: GA | C71: 1125 | D71: GA | E71: 1125 | F71: STANDARD CHARTERED BANK-BHD | G71: ASSET | H71: 7288.158
B72: GA | C72: 1128 | D72: GA | E72: 1128 | F72: STATE BANK OF INDIA CUR.A/C | G72: ASSET | H72: 1540.318
B73: GA | C73: 1129 | D73: GA | E73: 1129 | F73: STATE BANK OF INDIA - CALL A/C | G73: ASSET | H73: 363.938
B74: GA | C74: 1132 | D74: GA | E74: 1132 | F74: BMI BANK-CURRENT A/C | G74: ASSET | H74: 226416.93
B75: GA | C75: 1133 | D75: GA | E75: 1133 | F75: BMI BANK-USD A/C | G75: ASSET | H75: 27698.521
B76: GA | C76: 1156 | D76: GA | E76: 1156 | F76: NATIONAL BANK OF BAHRAIN-BHD | G76: ASSET | H76: 5000
A77: 01 | F77: LIABILITIES | H77: 0
A78: 02 | F78: CURRENT LIABLITIES | H78: 0
A79: 03 | F79: BANK OVERDRAFT | H79: 0
B80: GA | C80: 2100 | D80: GA | E80: 2100 | F80: BMI- FACILITY(MACHINERY PURCHA | G80: LIABILITY | H80: -515333.67
B81: GA | C81: 2102 | D81: GA | E81: 2102 | F81: AHLI UNITED BANK FACILITY A/C | G81: LIABILITY | H81: -7871
B82: GA | C82: 2106 | D82: GA | E82: 2106 | F82: SCB LONGTERM FACILITY | G82: LIABILITY | H82: -280879.31
B83: GA | C83: 2107 | D83: GA | E83: 2107 | F83: VAT OUTPUT | G83: ASSET | H83: -33660.804
B84: GA | C84: 2109 | D84: GA | E84: 2109 | F84: BMI-SHORT TERM/REVOLVING FACIL | G84: LIABILITY | H84: -223125
A85: 03 | F85: ISLAMIC FACILITY | H85: 0
A86: 03 | F86: ACCOUNTS PAYABLE | H86: 0
B87: IA | C87: 2211 | D87: IA | E87: 2211 | F87: TRADE CREDITORS | G87: LIABILITY | H87: -160169.14
B88: GA | C88: 2221 | D88: GA | E88: 2221 | F88: ACCRUED EXPENSES | G88: LIABILITY | H88: -7226.595
B89: GA | C89: 2251 | D89: GA | E89: 2251 | F89: PROVISION FOR INDEMNITY | G89: LIABILITY | H89: -192336.54
B90: GA | C90: 2252 | D90: GA | E90: 2252 | F90: PROVISION FOR LEAVE SALARY | G90: LIABILITY | H90: -43022.299
B91: GA | C91: 2254 | D91: GA | E91: 2254 | F91: PROVISION FOR PASSAGE | G91: LIABILITY | H91: -27143.236
B92: GA | C92: 2258 | D92: GA | E92: 2258 | F92: PROVISION FOR BONUS | G92: LIABILITY | H92: -57815.581
B93: GA | C93: 2276 | D93: GA | E93: 2276 | F93: PROVISION FOR REP TO MACHINER | G93: LIABILITY | H93: -1350
B94: GA | C94: 2291 | D94: GA | E94: 2291 | F94: PROVISION FOR DOUBTFUL DEBTS | G94: ASSET | H94: -69340.204
B95: GA | C95: 2301 | D95: GA | E95: 2301 | F95: PURCHASE CONTROL A/C | G95: LIABILITY | H95: -43769.614
B96: GA | C96: 2311 | D96: GA | E96: 2311 | F96: SUSPENSE A/C - GENERAL | G96: LIABILITY | H96: 878.5
B97: GA | C97: 2315 | D97: GA | E97: 2315 | F97: SUSPENSE A/C- BSM | G97: LIABILITY | H97: -31.5
B98: GA | C98: 2317 | D98: GA | E98: 2317 | F98: CSM -VENTURE-SUSPENSE A/C | G98: LIABILITY | H98: 5458.63
... B101: GA | C101: 2331 | D101: GA | E101: 2331 | F101: SUSPENSE A/C-AL SHARIF JETTY P | G101: ASSET | H101: 12110.84
A102: 03 | F102: VEHICLE LOANS | H102: 0
B103: GA | C103: 2351 | D103: GA | E103: 2351 | F103: Y K ALMOAYYED-VEH LOAN-UD TRUK | G103: LIABILITY | H103: -16938
A104: 03 | F104: TERM LOANS | H104: 0
A105: 02 | F105: EQUITY | H105: 0
B106: GA | C106: 2501 | D106: GA | E106: 2501 | F106: SHARE CAPITAL | G106: EQUITY | H106: -600000
B107: GA | C107: 2521 | D107: GA | E107: 2521 | F107: RETAINED EARNINGS | G107: EQUITY | H107: -4958367.6
B108: GA | C108: 2421 | D108: GA | E108: 2421 | F108: LEGAL RESERVE | G108: EQUITY | H108: -300000
B109: GA | C109: 2423 | D109: GA | E109: 2423 | F109: CURRENT A/C-FAREED Y K ALMOAYY | G109: ASSET | H109: 361
B110: CA | C110: 2410 | D110: CA | E110: 2410 | F110: SHARE HOLDERS' LOAN | G110: LIABILITY | H110: -364705.24
B111: GA | C111: 2411 | D111: GA | E111: 2411 | F111: CURRENT A/C - KHALID AL SHARIF | G111: LIABILITY | H111: 4161.14
B112: GA | C112: 2412 | D112: GA | E112: 2412 | F112: CURRENT A/C - GHASSAN E.A | G112: LIABILITY | H112: 4161.14
B113: GA | C113: 2413 | D113: GA | E113: 2413 | F113: CURRENT A/C-OVERLAND TRADING | G113: LIABILITY | H113: 71646.02
B114: GA | C114: 2414 | D114: GA | E114: 2414 | F114: CURRENT A/C - ALI AL SAAD | G114: LIABILITY | H114: 52.26
B115: GA | C115: 2416 | D115: GA | E115: 2416 | F115: CURRENT A/C-FAISAL AL MATROOK | G115: LIABILITY | H115: 4161.145
B116: GA | C116: 2417 | D116: GA | E116: 2417 | F116: CURRENT A/C-JAMEEL AL MATROOK | G116: LIABILITY | H116: 4161.14
B117: GA | C117: 2418 | D117: GA | E117: 2418 | F117: CURRENT A/C- UNITED COMMERCIAL | G117: LIABILITY | H117: 4161.15
B118: GA | C118: 2419 | D118: GA | E118: 2419 | F118: CURRENT A/C-ABDUL RAHMAN ALSAA | G118: LIABILITY | H118: 4161.145
A119: 01 | F119: INCOME | H119: 0
A120: 02 | F120: SALES | H120: 0
B121: CA | C121: 3111 | D121: CA | E121: 3111 | F121: EXPORT SALES | G121: INCOME | H121: -11037429
B122: CA | C122: 3151 | D122: CA | E122: 3151 | F122: LOCAL SALES | G122: INCOME | H122: -1128642.4
A123: 02 | F123: OTHER INCOME | H123: 0 | I123: cumulative exps & income( Year 2018&19)
B124: CA | C124: 3211 | D124: CA | E124: 3211 | F124: MISCELLANEOUS INCOME | G124: INCOME | H124: -87179.783 | I124: so take income & expenses from the attached p&l sheet
B125: CA | C125: 3210 | D125: CA | E125: 3210 | F125: PROCESSING/SERVICE INCOME | G125: INCOME | H125: -301406.77
B126: CA | C126: 3221 | D126: CA | E126: 3221 | F126: INTEREST RECEIVED | G126: INCOME | H126: -1253.349
...
